Workbook

Sheet Read me
A1: Key risk indicator (KRI) library
A2: RiskLens Australia · free template · version 1.0 (September 2026)
A4: What this is | B4: A library of 20 example key risk indicators across risk types, with threshold design notes, and space to record current values (the first three have example values). Status (Green, Amber, Red) calculates automatically. Background: https://hayesskvaril-ctrl.github.io/governance/board-risk-reporting.html
A5: How to use it | B5: 1. Choose the KRIs relevant to your risk profile and delete the rest. 2. Set green and red thresholds from your risk appetite. Values between them are amber. 3. Set the direction (higher is worse, or lower is worse). 4. Enter the current value each period. Status calculates automatically. 5. See 'Threshold design notes' for guidance.
A6: Example thresholds | B6: All thresholds in the examples are illustrative only. They are not benchmarks. Set your own from your risk appetite statement and data.
A7: Colour key | B7: Pale yellow cells: fill these in (many have drop-down lists). Grey-blue cells: calculated automatically; don't type over them. Green rows: worked examples. Replace or delete them.
A8: Important | B8: RiskLens Australia provides general educational information only. It is not legal, financial or compliance advice and does not take into account your circumstances. Always refer to the official legislation and regulator guidance, and seek professional advice where appropriate.
A10: Fill in
A11: Calculated
A12: Example

Sheet KRI library
A1: KRI library
A2: Fill in the yellow cells. Grey-blue cells calculate automatically.
A4: KRI ID | B4: Risk type | C4: KRI | D4: What it measures | E4: Leading or lagging | F4: Unit | G4: Frequency | H4: Green up to (or from) | I4: Red at (or below) | J4: Direction | K4: Current value | L4: Status | M4: Owner | N4: Design notes
A5: KRI-01 | B5: Operational | C5: Number of operational incidents raised | D5: Volume of incidents recorded in the period | E5: Lagging | F5: Count | G5: Monthly | H5: 10 | I5: 20 | J5: Higher is worse | K5: 8 | L5: =IF(OR(K5="",H5="",I5="",J5=""),"",IF(J5="Higher is worse",IF(K5>=I5,"Red",IF(K5>H5,"Amber","Green")),IF(K5<=I5,"Red",IF(K5<H5,"Amber","Green")))) -> Green | N5: A sudden fall can mean under-reporting, not improvement.
A6: KRI-02 | B6: Operational | C6: Processing backlog older than 5 business days | D6: Transactions not processed within service standards | E6: Leading | F6: Count | G6: Weekly | H6: 50 | I6: 200 | J6: Higher is worse | K6: 120 | L6: =IF(OR(K6="",H6="",I6="",J6=""),"",IF(J6="Higher is worse",IF(K6>=I6,"Red",IF(K6>H6,"Amber","Green")),IF(K6<=I6,"Red",IF(K6<H6,"Amber","Green")))) -> Amber | N6: Link thresholds to member harm and legal timeframes (e.g. rollovers).
A7: KRI-03 | B7: Operational | C7: Manual workarounds in critical processes | D7: Number of manual workarounds in place for critical operations | E7: Leading | F7: Count | G7: Quarterly | H7: 3 | I7: 6 | J7: Higher is worse | K7: 7 | L7: =IF(OR(K7="",H7="",I7="",J7=""),"",IF(J7="Higher is worse",IF(K7>=I7,"Red",IF(K7>H7,"Amber","Green")),IF(K7<=I7,"Red",IF(K7<H7,"Amber","Green")))) -> Red
A8: KRI-04 | B8: Compliance | C8: Breaches identified in the period | D8: New breaches or possible breaches recorded | E8: Lagging | F8: Count | G8: Monthly | H8: 5 | I8: 10 | J8: Higher is worse | L8: =IF(OR(K8="",H8="",I8="",J8=""),"",IF(J8="Higher is worse",IF(K8>=I8,"Red",IF(K8>H8,"Amber","Green")),IF(K8<=I8,"Red",IF(K8<H8,"Amber","Green"))))
A9: KRI-05 | B9: Compliance | C9: Regulatory reports lodged late | D9: Reports to ASIC, APRA, OAIC or AUSTRAC lodged after the deadline | E9: Lagging | F9: Count | G9: Monthly | H9: 0 | I9: 1 | J9: Higher is worse | L9: =IF(OR(K9="",H9="",I9="",J9=""),"",IF(J9="Higher is worse",IF(K9>=I9,"Red",IF(K9>H9,"Amber","Green")),IF(K9<=I9,"Red",IF(K9<H9,"Amber","Green")))) | N9: Any late lodgement should usually be red.
A10: KRI-06 | B10: Compliance | C10: Overdue compliance actions | D10: Compliance issues past their agreed due date | E10: Leading | F10: Count | G10: Monthly | H10: 3 | I10: 8 | J10: Higher is worse | L10: =IF(OR(K10="",H10="",I10="",J10=""),"",IF(J10="Higher is worse",IF(K10>=I10,"Red",IF(K10>H10,"Amber","Green")),IF(K10<=I10,"Red",IF(K10<H10,"Amber","Green"))))
A11: KRI-07 | B11: Conduct | C11: Complaints per 1,000 members | D11: Complaint rate, normalised for size | E11: Lagging | F11: Rate | G11: Monthly | H11: 2 | I11: 4 | J11: Higher is worse | L11: =IF(OR(K11="",H11="",I11="",J11=""),"",IF(J11="Higher is worse",IF(K11>=I11,"Red",IF(K11>H11,"Amber","Green")),IF(K11<=I11,"Red",IF(K11<H11,"Amber","Green")))) | N11: Normalise so growth doesn't look like deterioration.
A12: KRI-08 | B12: Conduct | C12: Complaints resolved within RG 271 timeframes | D12: Share of complaints closed within the required maximum | E12: Lagging | F12: % | G12: Monthly | H12: 95 | I12: 90 | J12: Lower is worse | L12: =IF(OR(K12="",H12="",I12="",J12=""),"",IF(J12="Higher is worse",IF(K12>=I12,"Red",IF(K12>H12,"Amber","Green")),IF(K12<=I12,"Red",IF(K12<H12,"Amber","Green"))))
A13: KRI-09 | B13: Conduct | C13: AFCA complaints received | D13: External disputes lodged with AFCA | E13: Lagging | F13: Count | G13: Quarterly | H13: 10 | I13: 20 | J13: Higher is worse | L13: =IF(OR(K13="",H13="",I13="",J13=""),"",IF(J13="Higher is worse",IF(K13>=I13,"Red",IF(K13>H13,"Amber","Green")),IF(K13<=I13,"Red",IF(K13<H13,"Amber","Green"))))
A14: KRI-10 | B14: Technology and cyber | C14: Critical patches overdue | D14: Critical security patches not applied within the target timeframe | E14: Leading | F14: Count | G14: Weekly | H14: 0 | I14: 3 | J14: Higher is worse | L14: =IF(OR(K14="",H14="",I14="",J14=""),"",IF(J14="Higher is worse",IF(K14>=I14,"Red",IF(K14>H14,"Amber","Green")),IF(K14<=I14,"Red",IF(K14<H14,"Amber","Green")))) | N14: Link to Essential Eight target maturity.
A15: KRI-11 | B15: Technology and cyber | C15: Phishing simulation click rate | D15: Share of staff clicking a simulated phishing link | E15: Leading | F15: % | G15: Quarterly | H15: 5 | I15: 10 | J15: Higher is worse | L15: =IF(OR(K15="",H15="",I15="",J15=""),"",IF(J15="Higher is worse",IF(K15>=I15,"Red",IF(K15>H15,"Amber","Green")),IF(K15<=I15,"Red",IF(K15<H15,"Amber","Green"))))
A16: KRI-12 | B16: Technology and cyber | C16: Critical system availability | D16: Uptime of systems supporting critical operations | E16: Lagging | F16: % | G16: Monthly | H16: 99.5 | I16: 99 | J16: Lower is worse | L16: =IF(OR(K16="",H16="",I16="",J16=""),"",IF(J16="Higher is worse",IF(K16>=I16,"Red",IF(K16>H16,"Amber","Green")),IF(K16<=I16,"Red",IF(K16<H16,"Amber","Green")))) | N16: Compare with CPS 230 tolerance levels.
A17: KRI-13 | B17: Third party | C17: Material service providers with overdue reviews | D17: Providers whose annual due diligence or performance review is overdue | E17: Leading | F17: Count | G17: Quarterly | H17: 0 | I17: 2 | J17: Higher is worse | L17: =IF(OR(K17="",H17="",I17="",J17=""),"",IF(J17="Higher is worse",IF(K17>=I17,"Red",IF(K17>H17,"Amber","Green")),IF(K17<=I17,"Red",IF(K17<H17,"Amber","Green"))))
A18: KRI-14 | B18: Third party | C18: Service level breaches by material providers | D18: SLA misses in the period | E18: Lagging | F18: Count | G18: Monthly | H18: 2 | I18: 5 | J18: Higher is worse | L18: =IF(OR(K18="",H18="",I18="",J18=""),"",IF(J18="Higher is worse",IF(K18>=I18,"Red",IF(K18>H18,"Amber","Green")),IF(K18<=I18,"Red",IF(K18<H18,"Amber","Green"))))
A19: KRI-15 | B19: People | C19: Unplanned staff turnover in key teams | D19: Annualised voluntary turnover in critical roles | E19: Leading | F19: % | G19: Quarterly | H19: 15 | I19: 25 | J19: Higher is worse | L19: =IF(OR(K19="",H19="",I19="",J19=""),"",IF(J19="Higher is worse",IF(K19>=I19,"Red",IF(K19>H19,"Amber","Green")),IF(K19<=I19,"Red",IF(K19<H19,"Amber","Green"))))
A20: KRI-16 | B20: People | C20: Mandatory training overdue | D20: Staff with overdue compliance training | E20: Leading | F20: % | G20: Monthly | H20: 5 | I20: 10 | J20: Higher is worse | L20: =IF(OR(K20="",H20="",I20="",J20=""),"",IF(J20="Higher is worse",IF(K20>=I20,"Red",IF(K20>H20,"Amber","Green")),IF(K20<=I20,"Red",IF(K20<H20,"Amber","Green"))))
A21: KRI-17 | B21: Investment (super) | C21: Options below performance objective | D21: Investment options behind their return objective over the objective period | E21: Lagging | F21: Count | G21: Quarterly | H21: 1 | I21: 3 | J21: Higher is worse | L21: =IF(OR(K21="",H21="",I21="",J21=""),"",IF(J21="Higher is worse",IF(K21>=I21,"Red",IF(K21>H21,"Amber","Green")),IF(K21<=I21,"Red",IF(K21<H21,"Amber","Green"))))
A22: KRI-18 | B22: Liquidity (super) | C22: Liquid assets as % of option assets | D22: Liquidity buffer against switching and rollovers | E22: Leading | F22: % | G22: Monthly | H22: 10 | I22: 7 | J22: Lower is worse | L22: =IF(OR(K22="",H22="",I22="",J22=""),"",IF(J22="Higher is worse",IF(K22>=I22,"Red",IF(K22>H22,"Amber","Green")),IF(K22<=I22,"Red",IF(K22<H22,"Amber","Green")))) | N22: Set from stress test results, not historical averages.
A23: KRI-19 | B23: Fraud | C23: Bank detail changes followed by payment within 48 hours | D23: A common account takeover pattern | E23: Leading | F23: Count | G23: Weekly | H23: 5 | I23: 15 | J23: Higher is worse | L23: =IF(OR(K23="",H23="",I23="",J23=""),"",IF(J23="Higher is worse",IF(K23>=I23,"Red",IF(K23>H23,"Amber","Green")),IF(K23<=I23,"Red",IF(K23<H23,"Amber","Green"))))
A24: KRI-20 | B24: Remediation | C24: Remediation programs past target date | D24: Open remediation programs behind plan | E24: Leading | F24: Count | G24: Monthly | H24: 0 | I24: 2 | J24: Higher is worse | L24: =IF(OR(K24="",H24="",I24="",J24=""),"",IF(J24="Higher is worse",IF(K24>=I24,"Red",IF(K24>H24,"Amber","Green")),IF(K24<=I24,"Red",IF(K24<H24,"Amber","Green"))))
L25: =IF(OR(K25="",H25="",I25="",J25=""),"",IF(J25="Higher is worse",IF(K25>=I25,"Red",IF(K25>H25,"Amber","Green")),IF(K25<=I25,"Red",IF(K25<H25,"Amber","Green"))))
L26: =IF(OR(K26="",H26="",I26="",J26=""),"",IF(J26="Higher is worse",IF(K26>=I26,"Red",IF(K26>H26,"Amber","Green")),IF(K26<=I26,"Red",IF(K26<H26,"Amber","Green"))))
L27: =IF(OR(K27="",H27="",I27="",J27=""),"",IF(J27="Higher is worse",IF(K27>=I27,"Red",IF(K27>H27,"Amber","Green")),IF(K27<=I27,"Red",IF(K27<H27,"Amber","Green"))))
L28: =IF(OR(K28="",H28="",I28="",J28=""),"",IF(J28="Higher is worse",IF(K28>=I28,"Red",IF(K28>H28,"Amber","Green")),IF(K28<=I28,"Red",IF(K28<H28,"Amber","Green"))))
L29: =IF(OR(K29="",H29="",I29="",J29=""),"",IF(J29="Higher is worse",IF(K29>=I29,"Red",IF(K29>H29,"Amber","Green")),IF(K29<=I29,"Red",IF(K29<H29,"Amber","Green"))))
L30: =IF(OR(K30="",H30="",I30="",J30=""),"",IF(J30="Higher is worse",IF(K30>=I30,"Red",IF(K30>H30,"Amber","Green")),IF(K30<=I30,"Red",IF(K30<H30,"Amber","Green"))))
L31: =IF(OR(K31="",H31="",I31="",J31=""),"",IF(J31="Higher is worse",IF(K31>=I31,"Red",IF(K31>H31,"Amber","Green")),IF(K31<=I31,"Red",IF(K31<H31,"Amber","Green"))))
L32: =IF(OR(K32="",H32="",I32="",J32=""),"",IF(J32="Higher is worse",IF(K32>=I32,"Red",IF(K32>H32,"Amber","Green")),IF(K32<=I32,"Red",IF(K32<H32,"Amber","Green"))))
L33: =IF(OR(K33="",H33="",I33="",J33=""),"",IF(J33="Higher is worse",IF(K33>=I33,"Red",IF(K33>H33,"Amber","Green")),IF(K33<=I33,"Red",IF(K33<H33,"Amber","Green"))))
L34: =IF(OR(K34="",H34="",I34="",J34=""),"",IF(J34="Higher is worse",IF(K34>=I34,"Red",IF(K34>H34,"Amber","Green")),IF(K34<=I34,"Red",IF(K34<H34,"Amber","Green"))))
L35: =IF(OR(K35="",H35="",I35="",J35=""),"",IF(J35="Higher is worse",IF(K35>=I35,"Red",IF(K35>H35,"Amber","Green")),IF(K35<=I35,"Red",IF(K35<H35,"Amber","Green"))))
L36: =IF(OR(K36="",H36="",I36="",J36=""),"",IF(J36="Higher is worse",IF(K36>=I36,"Red",IF(K36>H36,"Amber","Green")),IF(K36<=I36,"Red",IF(K36<H36,"Amber","Green"))))
... L64: =IF(OR(K64="",H64="",I64="",J64=""),"",IF(J64="Higher is worse",IF(K64>=I64,"Red",IF(K64>H64,"Amber","Green")),IF(K64<=I64,"Red",IF(K64<H64,"Amber","Green"))))

Sheet Dashboard
A1: Dashboard
A2: Updates automatically from the register.
A4: Measure | B4: Value
A5: KRIs with a current value | B5: =COUNT('KRI library'!$K$5:$K$64) -> 3
A6: Red | B6: =COUNTIF('KRI library'!$L$5:$L$64,"Red") -> 1
A7: Amber | B7: =COUNTIF('KRI library'!$L$5:$L$64,"Amber") -> 1
A8: Green | B8: =COUNTIF('KRI library'!$L$5:$L$64,"Green") -> 1
A10: KRIs by risk type | B10: Count
A11: Operational | B11: =COUNTIF('KRI library'!$B$5:$B$64,A11) -> 3
A12: Compliance | B12: =COUNTIF('KRI library'!$B$5:$B$64,A12) -> 3
A13: Conduct | B13: =COUNTIF('KRI library'!$B$5:$B$64,A13) -> 3
A14: Technology and cyber | B14: =COUNTIF('KRI library'!$B$5:$B$64,A14) -> 3
A15: Third party | B15: =COUNTIF('KRI library'!$B$5:$B$64,A15) -> 2
A16: People | B16: =COUNTIF('KRI library'!$B$5:$B$64,A16) -> 2
A17: Investment (super) | B17: =COUNTIF('KRI library'!$B$5:$B$64,A17) -> 1
A18: Liquidity (super) | B18: =COUNTIF('KRI library'!$B$5:$B$64,A18) -> 1
A19: Fraud | B19: =COUNTIF('KRI library'!$B$5:$B$64,A19) -> 1
A20: Remediation | B20: =COUNTIF('KRI library'!$B$5:$B$64,A20) -> 1
A21: Other | B21: =COUNTIF('KRI library'!$B$5:$B$64,A21) -> 0

Sheet Lists
A1: Drop-down lists
A2: Edit these values to suit your organisation. The drop-downs read from this tab.
A4: Risk type | B4: Leading or lagging | C4: Frequency | D4: Direction
A5: Operational | B5: Leading | C5: Daily | D5: Higher is worse
A6: Compliance | B6: Lagging | C6: Weekly | D6: Lower is worse
A7: Conduct | C7: Monthly
A8: Technology and cyber | C8: Quarterly
A9: Third party | C9: Annually
A10: People
A11: Investment (super)
A12: Liquidity (super)
A13: Fraud
A14: Remediation
A15: Other

Sheet Threshold design notes
A1: Designing KRI thresholds
A2: Notes to help set green, amber and red thresholds.
A4: Link to appetite | B4: Red should mean 'outside appetite' and trigger defined escalation. Amber is an early warning with room to act.
A5: Direction | B5: Some KRIs are worse when higher (incidents), others when lower (service levels). Set the Direction column so the status calculates correctly.
A6: Evidence | B6: Base thresholds on history, peer data, tolerance levels and stress testing. Record the rationale in the design notes column.
A7: Leading and lagging | B7: Balance lagging indicators (what happened) with leading ones (what might happen). Leading indicators give time to act.
A8: Test predictive value | B8: Check whether indicators actually moved before past incidents. Replace ones that didn't.
A9: Review | B9: Review KRIs and thresholds at least annually, and after major incidents or changes to the business.
