Workbook

Sheet Read me
A1: Remediation program tracker
A2: RiskLens Australia · free template · version 1.0 (September 2026)
A4: What this is | B4: A tracker for customer remediation programs, from identifying the affected population to paying compensation, handling residual amounts and closing the program. Background: https://hayesskvaril-ctrl.github.io/standards/asic-rg-277.html
A5: How to use it | B5: 1. Create one row per remediation program and link it to the breach or incident. 2. Record the affected population, the period, the method and beneficial assumptions used. 3. Update numbers paid and amounts paid as the program progresses. Percentages and alerts calculate automatically. 4. Record how residual (unclaimed) amounts will be handled, assurance over calculations and payments, and whether the root cause is fixed.
A6: RG 277 | B6: ASIC's RG 277 expects remediation to be fair, timely and efficient, with beneficial assumptions where data is missing, compensation for the time value of money, reasonable endeavours to return money, and specific options for residual amounts. Check RG 277 for the details.
A7: Worked example | B7: The example row is fictional and follows the fee error case used on the RiskLens breach significance page.
A8: Colour key | B8: Pale yellow cells: fill these in (many have drop-down lists). Grey-blue cells: calculated automatically; don't type over them. Green rows: worked examples. Replace or delete them.
A9: Important | B9: RiskLens Australia provides general educational information only. It is not legal, financial or compliance advice and does not take into account your circumstances. Always refer to the official legislation and regulator guidance, and seek professional advice where appropriate.
A11: Fill in
A12: Calculated
A13: Example

Sheet Remediation tracker
A1: Remediation tracker
A2: Fill in the yellow cells. Grey-blue cells calculate automatically.
A4: Program ID | B4: Linked breach or incident | C4: Issue description | D4: Date identified | E4: Period affected | F4: Customers affected | G4: Method and beneficial assumptions | H4: Estimated compensation incl. interest ($) | I4: Customers paid | J4: Amount paid ($) | K4: % customers paid | L4: % of compensation paid | M4: Customers not yet paid | N4: Residual approach | O4: Status | P4: Target completion | Q4: Days open | R4: Overdue? | S4: Regulator notified? | T4: Date closed | U4: Assurance over calculations and payments? | V4: Root cause fixed? | W4: Program owner
A5: REM-01 | B5: BR-2026-014 | C5: Administration fee rate 0.05% higher than PDS rate for 8 months after a system change. | D5: 46154 | E5: Sep 2025 to Apr 2026 | F5: 12000 | G5: Recalculate fees at PDS rate for each member; add fund earnings on the overcharge; where transaction data is incomplete, assume the member was charged for the full period. | H5: 1260000 | I5: 9800 | J5: 1010000 | K5: =IF(OR(F5="",F5=0,I5=""),"",I5/F5) -> 0.81666667 | L5: =IF(OR(H5="",H5=0,J5=""),"",J5/H5) -> 0.8015873 | M5: =IF(F5="","",F5-N(I5)) -> 2200 | N5: Not yet decided | O5: Paying | P5: 46356 | Q5: =IF(D5="","",IF(O5="Closed",IF(T5="","",T5-D5),TODAY()-D5)) -> 139 | R5: =IF(OR(P5="",O5="Closed"),"",IF(P5<TODAY(),"OVERDUE",IF(P5-TODAY()<=30,"Due soon","On track"))) -> On track | S5: Yes | U5: In progress | V5: Yes | W5: Head of Member Services
K6: =IF(OR(F6="",F6=0,I6=""),"",I6/F6) | L6: =IF(OR(H6="",H6=0,J6=""),"",J6/H6) | M6: =IF(F6="","",F6-N(I6)) | Q6: =IF(D6="","",IF(O6="Closed",IF(T6="","",T6-D6),TODAY()-D6)) | R6: =IF(OR(P6="",O6="Closed"),"",IF(P6<TODAY(),"OVERDUE",IF(P6-TODAY()<=30,"Due soon","On track")))
K7: =IF(OR(F7="",F7=0,I7=""),"",I7/F7) | L7: =IF(OR(H7="",H7=0,J7=""),"",J7/H7) | M7: =IF(F7="","",F7-N(I7)) | Q7: =IF(D7="","",IF(O7="Closed",IF(T7="","",T7-D7),TODAY()-D7)) | R7: =IF(OR(P7="",O7="Closed"),"",IF(P7<TODAY(),"OVERDUE",IF(P7-TODAY()<=30,"Due soon","On track")))
K8: =IF(OR(F8="",F8=0,I8=""),"",I8/F8) | L8: =IF(OR(H8="",H8=0,J8=""),"",J8/H8) | M8: =IF(F8="","",F8-N(I8)) | Q8: =IF(D8="","",IF(O8="Closed",IF(T8="","",T8-D8),TODAY()-D8)) | R8: =IF(OR(P8="",O8="Closed"),"",IF(P8<TODAY(),"OVERDUE",IF(P8-TODAY()<=30,"Due soon","On track")))
K9: =IF(OR(F9="",F9=0,I9=""),"",I9/F9) | L9: =IF(OR(H9="",H9=0,J9=""),"",J9/H9) | M9: =IF(F9="","",F9-N(I9)) | Q9: =IF(D9="","",IF(O9="Closed",IF(T9="","",T9-D9),TODAY()-D9)) | R9: =IF(OR(P9="",O9="Closed"),"",IF(P9<TODAY(),"OVERDUE",IF(P9-TODAY()<=30,"Due soon","On track")))
K10: =IF(OR(F10="",F10=0,I10=""),"",I10/F10) | L10: =IF(OR(H10="",H10=0,J10=""),"",J10/H10) | M10: =IF(F10="","",F10-N(I10)) | Q10: =IF(D10="","",IF(O10="Closed",IF(T10="","",T10-D10),TODAY()-D10)) | R10: =IF(OR(P10="",O10="Closed"),"",IF(P10<TODAY(),"OVERDUE",IF(P10-TODAY()<=30,"Due soon","On track")))
K11: =IF(OR(F11="",F11=0,I11=""),"",I11/F11) | L11: =IF(OR(H11="",H11=0,J11=""),"",J11/H11) | M11: =IF(F11="","",F11-N(I11)) | Q11: =IF(D11="","",IF(O11="Closed",IF(T11="","",T11-D11),TODAY()-D11)) | R11: =IF(OR(P11="",O11="Closed"),"",IF(P11<TODAY(),"OVERDUE",IF(P11-TODAY()<=30,"Due soon","On track")))
K12: =IF(OR(F12="",F12=0,I12=""),"",I12/F12) | L12: =IF(OR(H12="",H12=0,J12=""),"",J12/H12) | M12: =IF(F12="","",F12-N(I12)) | Q12: =IF(D12="","",IF(O12="Closed",IF(T12="","",T12-D12),TODAY()-D12)) | R12: =IF(OR(P12="",O12="Closed"),"",IF(P12<TODAY(),"OVERDUE",IF(P12-TODAY()<=30,"Due soon","On track")))
K13: =IF(OR(F13="",F13=0,I13=""),"",I13/F13) | L13: =IF(OR(H13="",H13=0,J13=""),"",J13/H13) | M13: =IF(F13="","",F13-N(I13)) | Q13: =IF(D13="","",IF(O13="Closed",IF(T13="","",T13-D13),TODAY()-D13)) | R13: =IF(OR(P13="",O13="Closed"),"",IF(P13<TODAY(),"OVERDUE",IF(P13-TODAY()<=30,"Due soon","On track")))
K14: =IF(OR(F14="",F14=0,I14=""),"",I14/F14) | L14: =IF(OR(H14="",H14=0,J14=""),"",J14/H14) | M14: =IF(F14="","",F14-N(I14)) | Q14: =IF(D14="","",IF(O14="Closed",IF(T14="","",T14-D14),TODAY()-D14)) | R14: =IF(OR(P14="",O14="Closed"),"",IF(P14<TODAY(),"OVERDUE",IF(P14-TODAY()<=30,"Due soon","On track")))
K15: =IF(OR(F15="",F15=0,I15=""),"",I15/F15) | L15: =IF(OR(H15="",H15=0,J15=""),"",J15/H15) | M15: =IF(F15="","",F15-N(I15)) | Q15: =IF(D15="","",IF(O15="Closed",IF(T15="","",T15-D15),TODAY()-D15)) | R15: =IF(OR(P15="",O15="Closed"),"",IF(P15<TODAY(),"OVERDUE",IF(P15-TODAY()<=30,"Due soon","On track")))
K16: =IF(OR(F16="",F16=0,I16=""),"",I16/F16) | L16: =IF(OR(H16="",H16=0,J16=""),"",J16/H16) | M16: =IF(F16="","",F16-N(I16)) | Q16: =IF(D16="","",IF(O16="Closed",IF(T16="","",T16-D16),TODAY()-D16)) | R16: =IF(OR(P16="",O16="Closed"),"",IF(P16<TODAY(),"OVERDUE",IF(P16-TODAY()<=30,"Due soon","On track")))
K17: =IF(OR(F17="",F17=0,I17=""),"",I17/F17) | L17: =IF(OR(H17="",H17=0,J17=""),"",J17/H17) | M17: =IF(F17="","",F17-N(I17)) | Q17: =IF(D17="","",IF(O17="Closed",IF(T17="","",T17-D17),TODAY()-D17)) | R17: =IF(OR(P17="",O17="Closed"),"",IF(P17<TODAY(),"OVERDUE",IF(P17-TODAY()<=30,"Due soon","On track")))
... K44: =IF(OR(F44="",F44=0,I44=""),"",I44/F44) | L44: =IF(OR(H44="",H44=0,J44=""),"",J44/H44) | M44: =IF(F44="","",F44-N(I44)) | Q44: =IF(D44="","",IF(O44="Closed",IF(T44="","",T44-D44),TODAY()-D44)) | R44: =IF(OR(P44="",O44="Closed"),"",IF(P44<TODAY(),"OVERDUE",IF(P44-TODAY()<=30,"Due soon","On track")))

Sheet Dashboard
A1: Dashboard
A2: Updates automatically from the register.
A4: Measure | B4: Value
A5: Programs recorded | B5: =COUNTA('Remediation tracker'!$A$5:$A$44) -> 1
A6: Open programs | B6: =COUNTA('Remediation tracker'!$A$5:$A$44)-COUNTIF('Remediation tracker'!$O$5:$O$44,"Closed") -> 1
A7: Programs overdue | B7: =COUNTIF('Remediation tracker'!$R$5:$R$44,"OVERDUE") -> 0
A8: Customers affected | B8: =SUM('Remediation tracker'!$F$5:$F$44) -> 12000
A9: Customers paid | B9: =SUM('Remediation tracker'!$I$5:$I$44) -> 9800
A10: Estimated compensation ($) | B10: =SUM('Remediation tracker'!$H$5:$H$44) -> 1260000
A11: Amount paid ($) | B11: =SUM('Remediation tracker'!$J$5:$J$44) -> 1010000
A12: Root cause not yet fixed | B12: =COUNTIF('Remediation tracker'!$V$5:$V$44,"No")+COUNTIF('Remediation tracker'!$V$5:$V$44,"In progress") -> 0
A14: Programs by status | B14: Count
A15: Scoping | B15: =COUNTIF('Remediation tracker'!$O$5:$O$44,A15) -> 0
A16: Calculating | B16: =COUNTIF('Remediation tracker'!$O$5:$O$44,A16) -> 0
A17: Approved | B17: =COUNTIF('Remediation tracker'!$O$5:$O$44,A17) -> 0
A18: Paying | B18: =COUNTIF('Remediation tracker'!$O$5:$O$44,A18) -> 1
A19: Residual handling | B19: =COUNTIF('Remediation tracker'!$O$5:$O$44,A19) -> 0
A20: Closed | B20: =COUNTIF('Remediation tracker'!$O$5:$O$44,A20) -> 0

Sheet Lists
A1: Drop-down lists
A2: Edit these values to suit your organisation. The drop-downs read from this tab.
A4: Yes / No | B4: Status | C4: Residual approach
A5: Yes | B5: Scoping | C5: Not yet decided
A6: No | B6: Calculating | C6: Lodge as unclaimed money (ASIC, or ATO for super)
A7: In progress | B7: Approved | C7: Pay to charity or not-for-profit (where permitted)
A8: N/A | B8: Paying | C8: Other (document basis)
B9: Residual handling | C9: Not applicable
B10: Closed
